odoo9_addon_geoengine_swisstopo-9.0.1.0.0-py2.7-nspkg.pth
odoo_addons/geoengine_swisstopo/__openerp__.py
odoo_addons/geoengine_swisstopo/__init__.py
odoo_addons/geoengine_swisstopo/models/geo_raster_layer.py
odoo_addons/geoengine_swisstopo/models/__init__.py
odoo_addons/geoengine_swisstopo/data/geo_raster_layer_type.xml
odoo9_addon_geoengine_swisstopo-9.0.1.0.0.dist-info/top_level.txt
odoo9_addon_geoengine_swisstopo-9.0.1.0.0.dist-info/WHEEL
odoo9_addon_geoengine_swisstopo-9.0.1.0.0.dist-info/RECORD
odoo9_addon_geoengine_swisstopo-9.0.1.0.0.dist-info/metadata.json
odoo9_addon_geoengine_swisstopo-9.0.1.0.0.dist-info/DESCRIPTION.rst
odoo9_addon_geoengine_swisstopo-9.0.1.0.0.dist-info/METADATA
odoo9_addon_geoengine_swisstopo-9.0.1.0.0.dist-info/namespace_packages.txt
