Metadata-Version: 2.0
Name: odoo9-addon-geoengine-swisstopo
Version: 9.0.1.0.0
Summary: Geospatial - Swisstopo layers
Home-page: http://www.camptocamp.com/
Author: UNKNOWN
Author-email: UNKNOWN
License: UNKNOWN
Platform: UNKNOWN
Requires-Dist: odoo (<9.1a,>=9.0a)
Requires-Dist: odoo9-addon-base-geoengine
Classifier: Programming Language :: Python :: 2.7
Classifier: Framework :: Odoo
